README.rst
Tool.py
setup.py
chang/__init__.py
chang/chang.py
chang.egg-info/PKG-INFO
chang.egg-info/SOURCES.txt
chang.egg-info/dependency_links.txt
chang.egg-info/top_level.txt