Metadata-Version: 1.0
Name: chang
Version: 1.0.0
Summary: this is a niubi lib
Home-page: https://study.163.com/course/courseLearn.htm?courseId=1004569003#/learn/video?lessonId=1051875146&courseId=1004569003
Author: changhaiyang
Author-email: 635498322@qq.com
License: UNKNOWN
Platform: UNKNOWN
